{
  "author": "SpankMeDaddy69Times",
  "original_created_utc": 1630781352,
  "title": "Cryptocurrencies Gain Legal Status in Texas as New Laws Take Effect",
  "created_utc": 1630794636,
  "selftext_html": null,
  "score": 236,
  "preview": {
    "images": [
      {
        "source": {
          "url": "https://external-preview.redd.it/05bU9Op3wOMF6P3uyvkz2ABmEzv77DJX7Dza8mEjJas.jpg?auto=webp&s=0f29cf5ed704eb88f5d91288b6dc291884c4868f",
          "width": 1365,
          "height": 800
        },
        "resolutions": [
          {
            "url": "https://external-preview.redd.it/05bU9Op3wOMF6P3uyvkz2ABmEzv77DJX7Dza8mEjJas.jpg?width=108&crop=smart&auto=webp&s=d98a363600f14cb52a0f06324392abac0c6c04bf",
            "width": 108,
            "height": 63
          },
          {
            "url": "https://external-preview.redd.it/05bU9Op3wOMF6P3uyvkz2ABmEzv77DJX7Dza8mEjJas.jpg?width=216&crop=smart&auto=webp&s=27cd04c4a34cc36fa550822db4d9a05cec6501d4",
            "width": 216,
            "height": 126
          },
          {
            "url": "https://external-preview.redd.it/05bU9Op3wOMF6P3uyvkz2ABmEzv77DJX7Dza8mEjJas.jpg?width=320&crop=smart&auto=webp&s=24e42b540cce3d012f29d921443f82b43383a9ae",
            "width": 320,
            "height": 187
          },
          {
            "url": "https://external-preview.redd.it/05bU9Op3wOMF6P3uyvkz2ABmEzv77DJX7Dza8mEjJas.jpg?width=640&crop=smart&auto=webp&s=e456c9bffa44303f724a453aa166a0026c5b44e8",
            "width": 640,
            "height": 375
          },
          {
            "url": "https://external-preview.redd.it/05bU9Op3wOMF6P3uyvkz2ABmEzv77DJX7Dza8mEjJas.jpg?width=960&crop=smart&auto=webp&s=228d967476fbc678a91cebe8a6b56602aa68849d",
            "width": 960,
            "height": 562
          },
          {
            "url": "https://external-preview.redd.it/05bU9Op3wOMF6P3uyvkz2ABmEzv77DJX7Dza8mEjJas.jpg?width=1080&crop=smart&auto=webp&s=ee6c7c4c9f9cf8e2c8888a42eae7091ad7763ef7",
            "width": 1080,
            "height": 632
          }
        ],
        "variants": {},
        "id": "gYXPZ4_LlgUCD-Q1xuMXa-t9LA7iqbmV75ujJ_b3KHU"
      }
    ],
    "enabled": false
  },
  "permalink": "/r/CryptoCurrency/comments/phx9yn/cryptocurrencies_gain_legal_status_in_texas_as/",
  "subreddit": "CryptoCurrency",
  "id": "phx9yn",
  "is_self": false,
  "media": null,
  "is_video": false,
  "the_new_excerpt": "",
  "localize": [
    {
      "locale": "ja",
      "title": "テキサス州で新しい法律が施行され、暗号通貨が法的地位を獲得"
    },
    {
      "locale": "zh",
      "title": "随着新法律的生效，加密货币在德州获得合法地位"
    },
    {
      "locale": "zh-Hant",
      "title": "隨着新法律的生效，加密貨幣在德州獲得合法地位"
    }
  ]
}