{
  "author": "Botany102",
  "original_created_utc": 1641267982,
  "title": "In the \"Puttin' on the Ritz\" song by Fred Astaire in the 1930s there is a line that says \"high hats and colored collars, white spats and 15 dollars\". Was 15 dollars actually a lot of money to carry around back then, and what could it buy you?",
  "created_utc": 1641297341,
  "selftext_html": null,
  "score": 103,
  "permalink": "/r/AskHistorians/comments/rvkqob/in_the_puttin_on_the_ritz_song_by_fred_astaire_in/",
  "subreddit": "AskHistorians",
  "id": "rvkqob",
  "is_self": true,
  "media": null,
  "is_video": false,
  "sensitive": false,
  "the_new_excerpt": "",
  "localize": [
    {
      "locale": "ja",
      "title": "1930年代にフレッド・アステアが歌った「Puttin' on the Ritz」の中に、「高い帽子に色のついた襟、白いスパッツに15ドル」という一節がある。当時、15ドルは実際に持ち歩くのに大金だったのだろうか、そして、それで何が買えたのだろうか。"
    },
    {
      "locale": "zh",
      "title": "在弗雷德-阿斯泰尔于20世纪30年代演唱的 \"Puttin' on the Ritz \"歌曲中，有一句话是这样说的：\"高帽子和彩色衣领，白色大衣和15美元\"。在当时，15美元实际上是一个可以随身携带的很多钱，它能给你买什么？"
    },
    {
      "locale": "zh-Hant",
      "title": "在弗雷德-阿斯泰爾於20世紀30年代演唱的 \"Puttin' on the Ritz \"歌曲中，有一句話是這樣說的：\"高帽子和彩色衣領，白色大衣和15美元\"。在當時，15美元實際上是一個可以隨身攜帶的很多錢，它能給你買什麼？"
    }
  ]
}