{
  "id": "334252",
  "commentsCount": 15,
  "createdAt": "2022-03-05T17:15:23.434Z",
  "description": "A PWA Site having news headlines, twitter trends, reddit memes, quotes, fatcs, etc. using rss feeds, apis.",
  "featuredAt": "2022-03-05T08:00:00Z",
  "media": [
    {
      "type": "image",
      "url": "https://ph-files.imgix.net/0c8415f2-15f2-4b9d-b880-d798462fe99c.png?auto=format",
      "videoUrl": null
    },
    {
      "type": "image",
      "url": "https://ph-files.imgix.net/1d7e0c04-45ff-40aa-a33f-5ab02cfe3541.png?auto=format",
      "videoUrl": null
    },
    {
      "type": "image",
      "url": "https://ph-files.imgix.net/a331c463-313c-4778-b1f5-aef133ad5bb1.png?auto=format",
      "videoUrl": null
    }
  ],
  "name": "Just Bulletins",
  "productLinks": [
    {
      "type": "Website",
      "url": "https://www.producthunt.com/r/14ef52206f1a24?utm_campaign=producthunt-api&utm_medium=api-v2&utm_source=Application%3A+Buzzing+%28ID%3A+41381%29"
    }
  ],
  "user": {
    "name": "Rahul Chauhan",
    "url": "https://www.producthunt.com/@rahul_chauhan14?utm_campaign=producthunt-api&utm_medium=api-v2&utm_source=Application%3A+Buzzing+%28ID%3A+41381%29"
  },
  "reviewsCount": 21,
  "reviewsRating": 5,
  "slug": "just-bulletins",
  "tagline": "Start your day with the world!",
  "url": "https://www.producthunt.com/posts/just-bulletins?utm_campaign=producthunt-api&utm_medium=api-v2&utm_source=Application%3A+Buzzing+%28ID%3A+41381%29",
  "votesCount": 93,
  "website": "https://www.producthunt.com/r/14ef52206f1a24?utm_campaign=producthunt-api&utm_medium=api-v2&utm_source=Application%3A+Buzzing+%28ID%3A+41381%29",
  "topics": {
    "edges": [
      {
        "node": {
          "name": "Web App"
        }
      },
      {
        "node": {
          "name": "News"
        }
      }
    ]
  },
  "original_createdAt": "2022-03-05T08:00:00Z",
  "localize": [
    {
      "locale": "ja",
      "description": "ニュースヘッドライン、Twitterトレンド、redditミーム、引用、fatcsなどをRSSフィードやapisを使用して表示するPWAサイトです。",
      "tagline": "一日の始まりは、世界と一緒に!"
    },
    {
      "locale": "zh",
      "description": "一个使用rss feeds和apis的PWA网站，有新闻头条、twitter趋势、reddit memes、报价、fatcs等。",
      "tagline": "与世界一起开始你的一天!"
    },
    {
      "locale": "zh-Hant",
      "description": "一個使用rss feeds和apis的PWA網站，有新聞頭條、twitter趨勢、reddit memes、報價、fatcs等。",
      "tagline": "與世界一起開始你的一天!"
    }
  ],
  "source_updated_at": 1646991710990
}