{
  "id": "355457",
  "commentsCount": 17,
  "createdAt": "2022-08-10T13:42:27.408Z",
  "description": "All you need is a slide deck with speaker notes and a profile picture to immediately generate a professional video course. Automatically transform dull content into entertaining microlearning lectures with the help of AI technology at the click of a button.",
  "featuredAt": "2022-08-10T07:01:00Z",
  "media": [
    {
      "type": "video",
      "url": "https://ph-files.imgix.net/2152f8ed-5c56-409f-9eb1-6dff90300d15.jpeg?auto=format",
      "videoUrl": "https://youtu.be/gzTDcuGsy4A"
    },
    {
      "type": "image",
      "url": "https://ph-files.imgix.net/788623d9-eec0-4da1-b37c-d031a07c6b2c.gif?auto=format",
      "videoUrl": null
    },
    {
      "type": "image",
      "url": "https://ph-files.imgix.net/0433dbde-3117-4ebc-a314-f8ef644f1348.png?auto=format",
      "videoUrl": null
    },
    {
      "type": "image",
      "url": "https://ph-files.imgix.net/5162bbae-ce57-442b-92f6-39d6b5ddb36e.png?auto=format",
      "videoUrl": null
    },
    {
      "type": "image",
      "url": "https://ph-files.imgix.net/1fa71ebd-0a00-47d2-8f0b-36860773be73.png?auto=format",
      "videoUrl": null
    },
    {
      "type": "image",
      "url": "https://ph-files.imgix.net/13b93e04-1690-4622-b868-c8beb4160c85.png?auto=format",
      "videoUrl": null
    },
    {
      "type": "image",
      "url": "https://ph-files.imgix.net/b2122c03-4d72-4771-bb8d-7d2ef4b19f51.png?auto=format",
      "videoUrl": null
    },
    {
      "type": "image",
      "url": "https://ph-files.imgix.net/0bb2a2ec-83c1-437b-8aa5-3558e62b3e98.png?auto=format",
      "videoUrl": null
    },
    {
      "type": "image",
      "url": "https://ph-files.imgix.net/3039d36e-6da6-41bd-a35a-018b1736fdcd.png?auto=format",
      "videoUrl": null
    }
  ],
  "name": "UMU AI Audio Slides",
  "productLinks": [
    {
      "type": "Website",
      "url": "https://www.producthunt.com/r/a71521f42cdb1b?utm_campaign=producthunt-api&utm_medium=api-v2&utm_source=Application%3A+Buzzing+%28ID%3A+41381%29"
    }
  ],
  "user": {
    "name": "Nicolas Berthiaume",
    "url": "https://www.producthunt.com/@nicolasberthiaume?utm_campaign=producthunt-api&utm_medium=api-v2&utm_source=Application%3A+Buzzing+%28ID%3A+41381%29"
  },
  "reviewsCount": 0,
  "reviewsRating": 0,
  "slug": "umu-ai-audio-slides",
  "tagline": "Create subtitled AI video courses with a virtual instructor",
  "url": "https://www.producthunt.com/posts/umu-ai-audio-slides?utm_campaign=producthunt-api&utm_medium=api-v2&utm_source=Application%3A+Buzzing+%28ID%3A+41381%29",
  "votesCount": 74,
  "website": "https://www.producthunt.com/r/a71521f42cdb1b?utm_campaign=producthunt-api&utm_medium=api-v2&utm_source=Application%3A+Buzzing+%28ID%3A+41381%29",
  "topics": {
    "edges": [
      {
        "node": {
          "name": "Productivity"
        }
      },
      {
        "node": {
          "name": "Artificial Intelligence"
        }
      },
      {
        "node": {
          "name": "Online Learning"
        }
      }
    ]
  },
  "original_createdAt": "2022-08-10T07:01:00Z",
  "localize": [
    {
      "locale": "ja",
      "description": "スピーカーノートとプロフィール写真付きのスライドデッキがあれば、すぐにプロフェッショナルなビデオコースを作成することができます。ボタンをクリックするだけで、退屈なコンテンツがAI技術によって自動的に楽しいマイクロラーニングの講義に変身します。",
      "tagline": "バーチャルインストラクターによる字幕付きAI動画講座の作成"
    },
    {
      "locale": "zh",
      "description": "你只需要一个带有演讲者注释的幻灯片和一张个人照片，就可以立即生成一个专业的视频课程。在人工智能技术的帮助下，只需点击一个按钮，就能将枯燥的内容自动转化为娱乐性的微学习讲座。",
      "tagline": "用虚拟教员创建有字幕的AI视频课程"
    },
    {
      "locale": "zh-Hant",
      "description": "你只需要一個帶有演講者註釋的幻燈片和一張個人照片，就可以立即生成一個專業的視頻課程。在人工智能技術的幫助下，只需點擊一個按鈕，就能將枯燥的內容自動轉化爲娛樂性的微學習講座。",
      "tagline": "用虛擬教員創建有字幕的AI視頻課程"
    }
  ],
  "source_updated_at": 1660297502229
}