{
  "author": "KarvedHeart",
  "original_created_utc": 1627073115,
  "title": "What can you say during sex, but also in an interview?",
  "created_utc": 1627095085,
  "selftext_html": null,
  "score": 1142,
  "permalink": "/r/AskReddit/comments/oqb4a8/what_can_you_say_during_sex_but_also_in_an/",
  "subreddit": "AskReddit",
  "id": "oqb4a8",
  "is_self": true,
  "media": null,
  "is_video": false,
  "the_new_excerpt": "",
  "localize": [
    {
      "locale": "ja",
      "title": "セックス中だけでなく、インタビューではどんなことを話せばいいのでしょうか？"
    },
    {
      "locale": "zh",
      "title": "在性爱过程中，也可以在采访中说什么？"
    },
    {
      "locale": "zh-Hant",
      "title": "在性愛過程中，也可以在採訪中說什麼？"
    }
  ]
}