{
  "author": "Digi_Ammaz",
  "original_created_utc": 1641995861,
  "title": "Pakistan is about to ban crypto. What will happen to my staked asset on Binance?",
  "created_utc": 1642009002,
  "selftext_html": "&lt;!-- SC_OFF --&gt;&lt;div class=\"md\"&gt;&lt;p&gt;As the world is rapidly adopting technology, Pakistan keeps banning them. Now they have decided to permanently ban crypto currency. &lt;/p&gt;\n\n&lt;p&gt;To be very honest, they have fucking no clue the fuck they are doing. They are bunch of crackpots holding higher grade offices. &lt;/p&gt;\n\n&lt;p&gt;Now Im too worried as of every Pakistani right now. Wondering what should we do? One thing Im not doing for sure is selling them because of some random uneducated monkeys’ decided to ban it. &lt;/p&gt;\n\n&lt;p&gt;Can I use VPN? What are the cons of using VPN? Or do you guys have any other suggestions? Please help me out!&lt;/p&gt;\n&lt;/div&gt;&lt;!-- SC_ON --&gt;",
  "score": 342,
  "permalink": "/r/CryptoCurrency/comments/s26ujr/pakistan_is_about_to_ban_crypto_what_will_happen/",
  "subreddit": "CryptoCurrency",
  "id": "s26ujr",
  "is_self": true,
  "media": null,
  "is_video": false,
  "sensitive": false,
  "the_new_excerpt": "As the world is rapidly adopting technology, Pakistan keeps banning them. Now\nthey have decided to permanently ban crypto currency.\n\nTo be very honest, they have fucking no clue the fuck they are doing. They are\nbunch of crackpots holding higher grade offices.\n\nNow Im too worried as of every…"
}