{
  "author": "Thryloz",
  "original_created_utc": 1625337232,
  "title": "After the breakup of the USSR, the Lithuanian basketball team couldn't afford to participate in the 1992 Olympics, so the Grateful Dead funded the team's expenses and sent a box of tie-dyed outfits in Lithuania's national colours. They went on to win bronze.",
  "created_utc": 1625361159,
  "selftext_html": null,
  "score": 84396,
  "preview": {
    "images": [
      {
        "source": {
          "url": "https://external-preview.redd.it/a0mF0DYIg6EgAjTd_Js1Wygz2rIMJpBgGNZBy9F3B24.jpg?auto=webp&s=88725a3213f89a844a02a9699be7106a86370e42",
          "width": 720,
          "height": 482
        },
        "resolutions": [
          {
            "url": "https://external-preview.redd.it/a0mF0DYIg6EgAjTd_Js1Wygz2rIMJpBgGNZBy9F3B24.jpg?width=108&crop=smart&auto=webp&s=309a9772d9f87e118b76424c2fd15dfcb511a841",
            "width": 108,
            "height": 72
          },
          {
            "url": "https://external-preview.redd.it/a0mF0DYIg6EgAjTd_Js1Wygz2rIMJpBgGNZBy9F3B24.jpg?width=216&crop=smart&auto=webp&s=9e0a4d45369089591e02a634728719b30b6bd783",
            "width": 216,
            "height": 144
          },
          {
            "url": "https://external-preview.redd.it/a0mF0DYIg6EgAjTd_Js1Wygz2rIMJpBgGNZBy9F3B24.jpg?width=320&crop=smart&auto=webp&s=8f5fbf3a70f479d5976138b3080dcc8f9f4a3512",
            "width": 320,
            "height": 214
          },
          {
            "url": "https://external-preview.redd.it/a0mF0DYIg6EgAjTd_Js1Wygz2rIMJpBgGNZBy9F3B24.jpg?width=640&crop=smart&auto=webp&s=ccfd6ff234ab89125f4c5b66385204a2086ce7b8",
            "width": 640,
            "height": 428
          }
        ],
        "variants": {},
        "id": "Jhrr-2_SYvqhURFLNTTtSIqzfomTrp7xeYs014ZVoXo"
      }
    ],
    "enabled": true
  },
  "permalink": "/r/interestingasfuck/comments/od3na5/after_the_breakup_of_the_ussr_the_lithuanian/",
  "subreddit": "interestingasfuck",
  "id": "od3na5",
  "is_self": false,
  "media": null,
  "is_video": false,
  "the_new_excerpt": "",
  "localize": [
    {
      "locale": "ja",
      "title": "ソ連崩壊後、リトアニアのバスケットボールチームは、1992年のオリンピックに参加する余裕がありませんでした。そこで、グレイトフル・デッドはチームの費用を出資し、リトアニアのナショナルカラーのタイダイ衣装を箱に詰めて送りました。その結果、彼らは銅メダルを獲得しました。"
    },
    {
      "locale": "zh",
      "title": "苏联解体后，立陶宛篮球队无力参加1992年的奥运会，因此感恩而死乐队资助了球队的费用，并送来一箱立陶宛国家颜色的扎染服装。他们后来赢得了铜牌。"
    },
    {
      "locale": "zh-Hant",
      "title": "蘇聯解體後，立陶宛籃球隊無力參加1992年的奧運會，因此感恩而死樂隊資助了球隊的費用，並送來一箱立陶宛國家顏色的扎染服裝。他們後來贏得了銅牌。"
    }
  ]
}