{
  "author": "darkizzle",
  "the_new_excerpt": "",
  "original_created_utc": 1619195119,
  "localize": [
    {
      "locale": "ja",
      "title": "今までで一番簡単な40マイル。あなたのホモォォォォォォォォォォォォォォォォォォォォォォォォォォォォォォン"
    },
    {
      "locale": "zh",
      "title": "有史以来最容易的40百万。你们这些同乡会的人正在错过。"
    },
    {
      "locale": "zh-Hant",
      "title": "有史以來最容易的40百萬。你們這些同鄉會的人正在錯過。"
    }
  ],
  "title": "Easiest 40 mil ever. You homochondriacs are missing out",
  "created_utc": 1619240576,
  "selftext_html": null,
  "score": 86731,
  "preview": {
    "images": [
      {
        "source": {
          "url": "https://preview.redd.it/bnuj7qwu8yu61.jpg?auto=webp&s=8e4bd9274bf8a5fd2566fb67f4ae6192d9ba2636",
          "width": 4096,
          "height": 2048
        },
        "resolutions": [
          {
            "url": "https://preview.redd.it/bnuj7qwu8yu61.jpg?width=108&crop=smart&auto=webp&s=960114b0531678f65459e3c03ac8dd4aa34994e7",
            "width": 108,
            "height": 54
          },
          {
            "url": "https://preview.redd.it/bnuj7qwu8yu61.jpg?width=216&crop=smart&auto=webp&s=9d6f7d318a5df5bf1485815d417ecea4337c8e2b",
            "width": 216,
            "height": 108
          },
          {
            "url": "https://preview.redd.it/bnuj7qwu8yu61.jpg?width=320&crop=smart&auto=webp&s=4913c79a87e8a707c067cda87f7c4a056f398efc",
            "width": 320,
            "height": 160
          },
          {
            "url": "https://preview.redd.it/bnuj7qwu8yu61.jpg?width=640&crop=smart&auto=webp&s=8b6fe098522318b39779091fd80fc7f7b64b560d",
            "width": 640,
            "height": 320
          },
          {
            "url": "https://preview.redd.it/bnuj7qwu8yu61.jpg?width=960&crop=smart&auto=webp&s=e61d2f4b65c3be2d3d1e11e2a0971a755a1bce92",
            "width": 960,
            "height": 480
          },
          {
            "url": "https://preview.redd.it/bnuj7qwu8yu61.jpg?width=1080&crop=smart&auto=webp&s=f681dc2886623220055d903133ea41b988a2230a",
            "width": 1080,
            "height": 540
          }
        ],
        "variants": {},
        "id": "-7poHOClI8CILMiAtgqVOdkJU9_f3SQJZYJ-Uwj7UoY"
      }
    ],
    "enabled": true
  },
  "permalink": "/r/MurderedByWords/comments/mwz2oi/easiest_40_mil_ever_you_homochondriacs_are/",
  "subreddit": "MurderedByWords",
  "id": "mwz2oi",
  "is_self": false,
  "media": null,
  "is_video": false,
  "source_updated_at": 1619776196949
}