{
  "author": "forgottenGost",
  "original_created_utc": 1632746648,
  "title": "Forget questions, what's your favorite answer?",
  "created_utc": 1632756202,
  "selftext_html": null,
  "score": 1324,
  "permalink": "/r/AskReddit/comments/pwg9k1/forget_questions_whats_your_favorite_answer/",
  "subreddit": "AskReddit",
  "id": "pwg9k1",
  "is_self": true,
  "media": null,
  "is_video": false,
  "the_new_excerpt": "",
  "localize": [
    {
      "locale": "ja",
      "title": "Forget questions, what's your favorite answer?"
    },
    {
      "locale": "zh",
      "title": "忘记问题，你最喜欢的答案是什么？"
    },
    {
      "locale": "zh-Hant",
      "title": "忘記問題，你最喜歡的答案是什麼？"
    }
  ]
}