{
  "author": "Zeretaaa",
  "the_new_excerpt": "This applies to both your own love and love from others",
  "original_created_utc": 1610813983,
  "localize": [
    {
      "locale": "zh",
      "the_new_excerpt": "这既适用于自己的爱，也适用于别人的爱。",
      "title": "你是怎么解脱的，不管是什么原因，你是不值得爱的？"
    },
    {
      "locale": "zh-Hant",
      "the_new_excerpt": "這既適用於自己的愛，也適用於別人的愛。",
      "title": "你是怎麼解脫的，不管是什麼原因，你是不值得愛的？"
    }
  ],
  "title": "How did you unlearn, for whatever reason, that you were unworthy of love?",
  "created_utc": 1610854199,
  "selftext_html": "<!-- SC_OFF --><div class=\"md\"><p>This applies to both your own love and love from others</p>\n</div><!-- SC_ON -->",
  "score": 101,
  "permalink": "/r/AskWomen/comments/kylsh3/how_did_you_unlearn_for_whatever_reason_that_you/",
  "subreddit": "AskWomen",
  "id": "kylsh3",
  "is_self": true,
  "media": null,
  "is_video": false
}