{
  "author": "Harshbro9760",
  "original_created_utc": 1625646382,
  "title": "USA which is considered fairly advanced in women rights have never seen a women leader, but countries like India, Pakistan, Bangladesh which are considered to be backward in women rights have had women prime minsters. Why is this so?",
  "created_utc": 1625661238,
  "selftext_html": null,
  "score": 450,
  "permalink": "/r/AskHistorians/comments/ofern4/usa_which_is_considered_fairly_advanced_in_women/",
  "subreddit": "AskHistorians",
  "id": "ofern4",
  "is_self": true,
  "media": null,
  "is_video": false,
  "the_new_excerpt": "",
  "localize": [
    {
      "locale": "ja",
      "title": "女性の権利にかなり進んでいるとされるアメリカでは、女性のリーダーを見たことがありませんが、女性の権利に遅れているとされるインド、パキスタン、バングラデシュのような国では、女性の首相が誕生しています。これはなぜでしょうか？"
    },
    {
      "locale": "zh",
      "title": "在妇女权利方面被认为相当先进的美国从未出现过女性领导人，但像印度、巴基斯坦、孟加拉国这些在妇女权利方面被认为是落后的国家却有女性总理。为什么会这样呢？"
    },
    {
      "locale": "zh-Hant",
      "title": "在婦女權利方面被認爲相當先進的美國從未出現過女性領導人，但像印度、巴基斯坦、孟加拉國這些在婦女權利方面被認爲是落後的國家卻有女性總理。爲什麼會這樣呢？"
    }
  ]
}