{
  "created_at": "Wed Jun 23 6:55:11 +0000 2021",
  "id_str": "1407586466142765057",
  "full_text": "Please report &amp; block this impersonator @l00triIIionUSD \n\nVery nasty scammer. Almost undetectable (\"l\" instead of \"1\" and 2x capital i \"II\" instead of \"ll\") and aggressive approach: putting \"send me a dm\" under tweets, then tries to steal your BTC. @twitter @TwitterSupport https://t.co/KcIsEfukNt",
  "display_text_range": [
    0,
    277
  ],
  "entities": {
    "hashtags": [],
    "symbols": [],
    "user_mentions": [
      {
        "screen_name": "l00triIIionUSD",
        "name": "PlanB",
        "id": 1578980990,
        "id_str": "1578980990",
        "indices": [
          44,
          59
        ]
      },
      {
        "screen_name": "Twitter",
        "name": "Twitter",
        "id": 783214,
        "id_str": "783214",
        "indices": [
          253,
          261
        ]
      },
      {
        "screen_name": "TwitterSupport",
        "name": "Twitter Support",
        "id": 17874544,
        "id_str": "17874544",
        "indices": [
          262,
          277
        ]
      }
    ],
    "urls": [],
    "media": [
      {
        "id": 1407584881039790000,
        "id_str": "1407584881039790082",
        "indices": [
          278,
          301
        ],
        "media_url": "http://pbs.twimg.com/media/E4i-_dmWUAI5d8n.jpg",
        "media_url_https": "https://pbs.twimg.com/media/E4i-_dmWUAI5d8n.jpg",
        "url": "https://t.co/KcIsEfukNt",
        "display_url": "pic.twitter.com/KcIsEfukNt",
        "expanded_url": "https://twitter.com/100trillionUSD/status/1407586466142765057/photo/1",
        "type": "photo",
        "sizes": {
          "thumb": {
            "w": 150,
            "h": 150,
            "resize": "crop"
          },
          "large": {
            "w": 1100,
            "h": 1815,
            "resize": "fit"
          },
          "medium": {
            "w": 727,
            "h": 1200,
            "resize": "fit"
          },
          "small": {
            "w": 412,
            "h": 680,
            "resize": "fit"
          }
        }
      }
    ]
  },
  "user": {
    "name": "PlanB",
    "screen_name": "100trillionUSD",
    "profile_image_url_https": "https://pbs.twimg.com/profile_images/1407223894600302594/gBUVNH89_normal.jpg"
  },
  "retweet_count": 168,
  "favorite_count": 1235,
  "possibly_sensitive": false,
  "original_created_at": "Wed Jun 23 06:28:59 +0000 2021",
  "localize": [
    {
      "locale": "ja",
      "full_text": "このなりすましを報告＆ブロックしてください @l00triIIionUSD \n\n非常に悪質な詐欺師です。ほとんど見分けがつかず（\"1 \"の代わりに \"l\"、\"ll \"の代わりに2つの大文字の \"II\"）、攻撃的なアプローチで、ツイートの下に \"send me a dm \"を入れて、BTCを盗もうとします。@twitter @TwitterSupport https://t.co/KcIsEfukNt"
    },
    {
      "locale": "zh",
      "full_text": "请报告&amp; 封锁这个冒名顶替者 @l00triIIionUSD \n\n非常讨厌的骗子。几乎无法察觉（用 \"l \"代替 \"1\"，用2个大写的i \"II \"代替 \"ll\"），而且方法很激进：在推特下写上 \"给我发个短信\"，然后试图偷取你的BTC。@twitter @TwitterSupport https://t.co/KcIsEfukNt"
    },
    {
      "locale": "zh-Hant",
      "full_text": "請報告&amp; 封鎖這個冒名頂替者 @l00triIIionUSD \n\n非常討厭的騙子。幾乎無法察覺（用 \"l \"代替 \"1\"，用2個大寫的i \"II \"代替 \"ll\"），而且方法很激進：在推特下寫上 \"給我發個短信\"，然後試圖偷取你的BTC。@twitter @TwitterSupport https://t.co/KcIsEfukNt"
    }
  ],
  "source_updated_at": 1624614206527
}