{
  "author": "Smartnership",
  "original_created_utc": 1656262193,
  "title": "Death Valley is 282’ below sea level. Would it offset the rising ocean to build a canal and create the Death Valley Sea?",
  "created_utc": 1656277982,
  "selftext_html": null,
  "score": 212,
  "permalink": "/r/askscience/comments/vl8yjt/death_valley_is_282_below_sea_level_would_it/",
  "subreddit": "askscience",
  "id": "vl8yjt",
  "is_self": true,
  "media": null,
  "is_video": false,
  "sensitive": false,
  "the_new_excerpt": ""
}