{
  "created_at": "Sat Mar 05 22:52:34 +0000 2022",
  "id_str": "1500238991672725519",
  "full_text": "The world must be willing to bleed Vladimir Putin’s regime of the resources that enable him to wage war and abuse his own people even if that imposes costs on Western economies https://t.co/zjSRu9ZmFO",
  "display_text_range": [
    0,
    200
  ],
  "entities": {
    "hashtags": [],
    "symbols": [],
    "user_mentions": [],
    "urls": [
      {
        "url": "https://t.co/zjSRu9ZmFO",
        "expanded_url": "https://econ.st/3vxmCOQ",
        "display_url": "econ.st/3vxmCOQ",
        "indices": [
          177,
          200
        ]
      }
    ]
  },
  "user": {
    "name": "The Economist",
    "screen_name": "TheEconomist",
    "profile_image_url_https": "https://pbs.twimg.com/profile_images/879361767914262528/HdRauDM-_normal.jpg"
  },
  "retweet_count": 49,
  "favorite_count": 168,
  "possibly_sensitive": false,
  "original_created_at": "Sat Mar 05 22:37:03 +0000 2022"
}