{
  "created_at": "Thu Mar 17 21:4:57 +0000 2022",
  "id_str": "1504546897578577931",
  "full_text": "A new, more assertive Germany is just what Europe needs to help it face down the menace in Moscow. It is just a shame it took a war to wake Europe’s sleeping giant https://t.co/AfXNVGpc6g",
  "display_text_range": [
    0,
    187
  ],
  "entities": {
    "hashtags": [],
    "symbols": [],
    "user_mentions": [],
    "urls": [
      {
        "url": "https://t.co/AfXNVGpc6g",
        "expanded_url": "https://econ.st/3wvCJx1",
        "display_url": "econ.st/3wvCJx1",
        "indices": [
          164,
          187
        ]
      }
    ]
  },
  "user": {
    "name": "The Economist",
    "screen_name": "TheEconomist",
    "profile_image_url_https": "https://pbs.twimg.com/profile_images/879361767914262528/HdRauDM-_normal.jpg"
  },
  "retweet_count": 35,
  "favorite_count": 81,
  "possibly_sensitive": false,
  "original_created_at": "Thu Mar 17 19:55:08 +0000 2022",
  "localize": [
    {
      "locale": "ja",
      "full_text": "ヨーロッパがモスクワの脅威に立ち向かうためには、新しい、より自己主張の強いドイツが必要なのである。ヨーロッパの眠れる巨人を目覚めさせるのに、戦争が必要だったのは残念だ。https://t.co/AfXNVGpc6g"
    },
    {
      "locale": "zh",
      "full_text": "一个新的、更自信的德国正是欧洲需要的，以帮助它面对莫斯科的威胁。只是遗憾的是，需要一场战争来唤醒欧洲沉睡的巨人 https://t.co/AfXNVGpc6g"
    },
    {
      "locale": "zh-Hant",
      "full_text": "一個新的、更自信的德國正是歐洲需要的，以幫助它面對莫斯科的威脅。只是遺憾的是，需要一場戰爭來喚醒歐洲沉睡的巨人 https://t.co/AfXNVGpc6g"
    }
  ]
}