{
  "author": "mynameisminho_",
  "original_created_utc": 1642390755,
  "title": "Today's billionaires buy private yachts and million dollar paintings. What frivolous purchases would an obscenely rich ancient Roman make?",
  "created_utc": 1642420021,
  "selftext_html": null,
  "score": 107,
  "permalink": "/r/AskHistorians/comments/s5tybu/todays_billionaires_buy_private_yachts_and/",
  "subreddit": "AskHistorians",
  "id": "s5tybu",
  "is_self": true,
  "media": null,
  "is_video": false,
  "sensitive": false,
  "the_new_excerpt": "",
  "localize": [
    {
      "locale": "ja",
      "title": "今日の億万長者は、プライベートヨットや100万ドルの絵画を買う。古代ローマ人はどんな贅沢な買い物をしたのだろうか？"
    },
    {
      "locale": "zh",
      "title": "今天的亿万富翁购买私人游艇和百万美元的绘画。一个富可敌国的古罗马人会做哪些轻浮的购买行为？"
    },
    {
      "locale": "zh-Hant",
      "title": "今天的億萬富翁購買私人遊艇和百萬美元的繪畫。一個富可敵國的古羅馬人會做哪些輕浮的購買行爲？"
    }
  ]
}