{
  "author": "nivesh_dewangan",
  "original_created_utc": 1652335243,
  "title": "couple goals",
  "created_utc": 1652363801,
  "selftext_html": null,
  "score": 81243,
  "preview": {
    "images": [
      {
        "source": {
          "url": "https://external-preview.redd.it/ZhVy6ibe09PDksWR1aT753mVBXoQI2CBcG-x-Ki6tSc.png?format=pjpg&amp;auto=webp&amp;s=e2597e38db09a18d48c368166d5ef3a2ae00e4ee",
          "width": 720,
          "height": 1280
        },
        "resolutions": [
          {
            "url": "https://external-preview.redd.it/ZhVy6ibe09PDksWR1aT753mVBXoQI2CBcG-x-Ki6tSc.png?width=108&amp;crop=smart&amp;format=pjpg&amp;auto=webp&amp;s=dcd42efd9eaa522d43a851d7a1063d2bde6bc92c",
            "width": 108,
            "height": 192
          },
          {
            "url": "https://external-preview.redd.it/ZhVy6ibe09PDksWR1aT753mVBXoQI2CBcG-x-Ki6tSc.png?width=216&amp;crop=smart&amp;format=pjpg&amp;auto=webp&amp;s=3737d8718c14f7e28d69417ee6c827a96271cbe3",
            "width": 216,
            "height": 384
          },
          {
            "url": "https://external-preview.redd.it/ZhVy6ibe09PDksWR1aT753mVBXoQI2CBcG-x-Ki6tSc.png?width=320&amp;crop=smart&amp;format=pjpg&amp;auto=webp&amp;s=fa2ea8a124bace721c0467db712c5c34385ccf56",
            "width": 320,
            "height": 568
          },
          {
            "url": "https://external-preview.redd.it/ZhVy6ibe09PDksWR1aT753mVBXoQI2CBcG-x-Ki6tSc.png?width=640&amp;crop=smart&amp;format=pjpg&amp;auto=webp&amp;s=670c92a1cc6249609824fbd5b4c144280cf0b7b3",
            "width": 640,
            "height": 1137
          }
        ],
        "variants": {},
        "id": "lXnUY0rpZKN2gOiNSnJ3OShi-ziBH4n4BPEyo6HX6fE"
      }
    ],
    "enabled": false
  },
  "permalink": "/r/MadeMeSmile/comments/unu8wc/couple_goals/",
  "subreddit": "MadeMeSmile",
  "id": "unu8wc",
  "is_self": false,
  "media": {
    "reddit_video": {
      "bitrate_kbps": 4800,
      "fallback_url": "https://v.redd.it/l4x2kaohjzy81/DASH_1080.mp4?source=fallback",
      "height": 1080,
      "width": 607,
      "scrubber_media_url": "https://v.redd.it/l4x2kaohjzy81/DASH_96.mp4",
      "dash_url": "https://v.redd.it/l4x2kaohjzy81/DASHPlaylist.mpd?a=1654955799%2CNjU5MTk1ZmY0NGZjMzNlZDMxZjgwMGZjMTYyNzExYWIwY2Q5YjBhYmQyMmE0MjFmZWJmODlkZmU2NmRkZDVkZQ%3D%3D&amp;v=1&amp;f=hd",
      "duration": 19,
      "hls_url": "https://v.redd.it/l4x2kaohjzy81/HLSPlaylist.m3u8?a=1654955799%2CZDgxYjI5OTZlM2Q5MTY1NDNjZTFkNDYxOTAxOGJlNGYyNGI2ODJiZmE5ZTgzMmNjNzVhY2FlYmMzZTE2ZWE5Mw%3D%3D&amp;v=1&amp;f=hd",
      "is_gif": false,
      "transcoding_status": "completed"
    }
  },
  "is_video": true,
  "sensitive": false,
  "the_new_excerpt": "",
  "localize": [
    {
      "locale": "ja",
      "title": "二人の目標"
    },
    {
      "locale": "zh",
      "title": "夫妇目标"
    },
    {
      "locale": "zh-Hant",
      "title": "夫婦目標"
    }
  ]
}