{
  "author": "Scouser360",
  "the_new_excerpt": "",
  "original_created_utc": 1611983516,
  "localize": [
    {
      "locale": "zh",
      "title": "当交易出现问题时"
    },
    {
      "locale": "zh-Hant",
      "title": "當交易出現問題時"
    }
  ],
  "title": "When the trade goes wrong",
  "created_utc": 1612013900,
  "selftext_html": null,
  "score": 446,
  "preview": {
    "images": [
      {
        "source": {
          "url": "https://preview.redd.it/q49nndb3lee61.jpg?auto=webp&s=22b60fefe38c717be854a3b3b8f1da43cc25039e",
          "width": 1080,
          "height": 656
        },
        "resolutions": [
          {
            "url": "https://preview.redd.it/q49nndb3lee61.jpg?width=108&crop=smart&auto=webp&s=599475398f34757d47072092442755bc095d2162",
            "width": 108,
            "height": 65
          },
          {
            "url": "https://preview.redd.it/q49nndb3lee61.jpg?width=216&crop=smart&auto=webp&s=ab0cb7c84421d909c53eeeb4fdfd0d6c2aa4d078",
            "width": 216,
            "height": 131
          },
          {
            "url": "https://preview.redd.it/q49nndb3lee61.jpg?width=320&crop=smart&auto=webp&s=f974fac42612ec1ba057de6e8d445a5f33ed687f",
            "width": 320,
            "height": 194
          },
          {
            "url": "https://preview.redd.it/q49nndb3lee61.jpg?width=640&crop=smart&auto=webp&s=2c588b7e4dc69a378c14045efc5c24be58d18954",
            "width": 640,
            "height": 388
          },
          {
            "url": "https://preview.redd.it/q49nndb3lee61.jpg?width=960&crop=smart&auto=webp&s=7bf1e090f45c9e1e857556c831c2467e898d4b0d",
            "width": 960,
            "height": 583
          },
          {
            "url": "https://preview.redd.it/q49nndb3lee61.jpg?width=1080&crop=smart&auto=webp&s=c6303d410658f9c5e7ea2ed3b6e3311bdd9437a0",
            "width": 1080,
            "height": 656
          }
        ],
        "variants": {},
        "id": "d1kX0dQR2Isittt2-M38cK5oAsZznfmvcspDjVGFF7k"
      }
    ],
    "enabled": true
  },
  "permalink": "/r/CryptoCurrency/comments/l8eilr/when_the_trade_goes_wrong/",
  "subreddit": "CryptoCurrency",
  "id": "l8eilr",
  "is_self": false,
  "media": null,
  "is_video": false,
  "source_updated_at": 1612518527095
}