{
  "author": "angelwriter",
  "original_created_utc": 1637675860,
  "title": "El Salvador Dollar-Denominated Bonds Crash as Country Launches Bitcoin Alternative",
  "created_utc": 1637685554,
  "selftext_html": null,
  "score": 186,
  "preview": {
    "images": [
      {
        "source": {
          "url": "https://external-preview.redd.it/JssgVRkfXVHgN1gWHAwFLWIc9xoPLqpHqRA6prTJ39U.jpg?auto=webp&s=23d388900d38762d32ceb6fe906559fd89630b8e",
          "width": 905,
          "height": 508
        },
        "resolutions": [
          {
            "url": "https://external-preview.redd.it/JssgVRkfXVHgN1gWHAwFLWIc9xoPLqpHqRA6prTJ39U.jpg?width=108&crop=smart&auto=webp&s=0a23538d4f003bb286e988c69460a587e79300eb",
            "width": 108,
            "height": 60
          },
          {
            "url": "https://external-preview.redd.it/JssgVRkfXVHgN1gWHAwFLWIc9xoPLqpHqRA6prTJ39U.jpg?width=216&crop=smart&auto=webp&s=7ac935be2e46b8240978962676d898b0d6a86fe5",
            "width": 216,
            "height": 121
          },
          {
            "url": "https://external-preview.redd.it/JssgVRkfXVHgN1gWHAwFLWIc9xoPLqpHqRA6prTJ39U.jpg?width=320&crop=smart&auto=webp&s=25829bc7352ed740047638c6b2b7442475c0badb",
            "width": 320,
            "height": 179
          },
          {
            "url": "https://external-preview.redd.it/JssgVRkfXVHgN1gWHAwFLWIc9xoPLqpHqRA6prTJ39U.jpg?width=640&crop=smart&auto=webp&s=0fa2259be7e11c09e1fd7ceba346ab72e7443e72",
            "width": 640,
            "height": 359
          }
        ],
        "variants": {},
        "id": "YzKEPbmFJid4NkvxPnA_NSfB7bApvrWF8u55OkfKBAQ"
      }
    ],
    "enabled": false
  },
  "permalink": "/r/Bitcoin/comments/r0dsxk/el_salvador_dollardenominated_bonds_crash_as/",
  "subreddit": "Bitcoin",
  "id": "r0dsxk",
  "is_self": false,
  "media": null,
  "is_video": false,
  "the_new_excerpt": "",
  "localize": [
    {
      "locale": "ja",
      "title": "エルサルバドルのドル建て債券が暴落、ビットコインで代替する国が登場"
    },
    {
      "locale": "zh",
      "title": "萨尔瓦多推出比特币替代品，美元计价债券暴跌"
    },
    {
      "locale": "zh-Hant",
      "title": "薩爾瓦多推出比特幣替代品，美元計價債券暴跌"
    }
  ]
}