{
  "created_at": "Wed Oct 13 18:47:6 +0000 2021",
  "id": 1448346961912991700,
  "id_str": "1448346961912991745",
  "full_text": "William Shatner, 90, was emotional after returning to Earth. \"What you have given me is the most profound experience I can imagine,\" he told Jeff Bezos. \"I hope I never recover from this, I hope that I can maintain what I feel now. I don’t want to lose it.\"https://t.co/NdoH6vb7I6",
  "truncated": false,
  "display_text_range": [
    0,
    280
  ],
  "entities": {
    "hashtags": [],
    "symbols": [],
    "user_mentions": [],
    "urls": [
      {
        "url": "https://t.co/NdoH6vb7I6",
        "expanded_url": "https://nyti.ms/3lEKhr2",
        "display_url": "nyti.ms/3lEKhr2",
        "indices": [
          257,
          280
        ]
      }
    ]
  },
  "source": "<a href=\"http://www.socialflow.com\" rel=\"nofollow\">SocialFlow</a>",
  "in_reply_to_status_id": null,
  "in_reply_to_status_id_str": null,
  "in_reply_to_user_id": null,
  "in_reply_to_user_id_str": null,
  "in_reply_to_screen_name": null,
  "user": {
    "id": 807095,
    "id_str": "807095",
    "name": "The New York Times",
    "screen_name": "nytimes",
    "location": "New York City",
    "description": "News tips? Share them here: https://t.co/ghL9OoYKMM",
    "url": "http://t.co/ahvuWqicF9",
    "entities": {
      "url": {
        "urls": [
          {
            "url": "http://t.co/ahvuWqicF9",
            "expanded_url": "http://www.nytimes.com/",
            "display_url": "nytimes.com",
            "indices": [
              0,
              22
            ]
          }
        ]
      },
      "description": {
        "urls": [
          {
            "url": "https://t.co/ghL9OoYKMM",
            "expanded_url": "http://nyti.ms/2FVHq9v",
            "display_url": "nyti.ms/2FVHq9v",
            "indices": [
              28,
              51
            ]
          }
        ]
      }
    },
    "protected": false,
    "followers_count": 50718489,
    "friends_count": 852,
    "listed_count": 211326,
    "created_at": "Fri Mar 02 20:41:42 +0000 2007",
    "favourites_count": 18582,
    "utc_offset": null,
    "time_zone": null,
    "geo_enabled": false,
    "verified": true,
    "statuses_count": 449790,
    "lang": null,
    "contributors_enabled": false,
    "is_translator": false,
    "is_translation_enabled": true,
    "profile_background_color": "131516",
    "profile_background_image_url": "http://abs.twimg.com/images/themes/theme14/bg.gif",
    "profile_background_image_url_https": "https://abs.twimg.com/images/themes/theme14/bg.gif",
    "profile_background_tile": true,
    "profile_image_url": "http://pbs.twimg.com/profile_images/1098244578472280064/gjkVMelR_normal.png",
    "profile_image_url_https": "https://pbs.twimg.com/profile_images/1098244578472280064/gjkVMelR_normal.png",
    "profile_banner_url": "https://pbs.twimg.com/profile_banners/807095/1584666392",
    "profile_link_color": "607696",
    "profile_sidebar_border_color": "FFFFFF",
    "profile_sidebar_fill_color": "EFEFEF",
    "profile_text_color": "333333",
    "profile_use_background_image": true,
    "has_extended_profile": false,
    "default_profile": false,
    "default_profile_image": false,
    "following": true,
    "follow_request_sent": false,
    "notifications": false,
    "translator_type": "none",
    "withheld_in_countries": []
  },
  "geo": null,
  "coordinates": null,
  "place": null,
  "contributors": null,
  "is_quote_status": false,
  "retweet_count": 125,
  "favorite_count": 806,
  "favorited": false,
  "retweeted": false,
  "possibly_sensitive": false,
  "lang": "en",
  "original_created_at": "Wed Oct 13 17:56:39 +0000 2021",
  "localize": [
    {
      "locale": "ja",
      "full_text": "ウィリアム・シャトナー（90歳）は、地球に戻ってきた後、感情的になりました。「あなたが私に与えてくれたものは、私が想像できる最も深い経験です」とジェフ・ベゾスに語りました。「私はこの経験から立ち直ることができないことを願い、今感じていることを維持できることを願っています。私はそれを失いたくありません。」https://t.co/NdoH6vb7I6"
    },
    {
      "locale": "zh",
      "full_text": "90岁的威廉-夏特纳在返回地球后情绪激动。\"你给我的是我能想象到的最深刻的经历，\"他告诉杰夫-贝佐斯。\"我希望我永远不会从中恢复，我希望我能保持我现在的感觉。我不想失去它。\"https://t.co/NdoH6vb7I6"
    },
    {
      "locale": "zh-Hant",
      "full_text": "90歲的威廉-夏特納在返回地球后情緒激動。\"你給我的是我能想象到的最深刻的經歷，\"他告訴傑夫-貝佐斯。\"我希望我永遠不會從中恢復，我希望我能保持我現在的感覺。我不想失去它。\"https://t.co/NdoH6vb7I6"
    }
  ]
}