{
  "author": "onarainyafternoon",
  "original_created_utc": 1647527958,
  "title": "[Serious] Scientists of Reddit, what's something you suspect is true in your field of study but you don't have enough evidence to prove it yet?",
  "created_utc": 1647560768,
  "selftext_html": null,
  "score": 1004,
  "permalink": "/r/AskReddit/comments/tgbq4p/serious_scientists_of_reddit_whats_something_you/",
  "subreddit": "AskReddit",
  "id": "tgbq4p",
  "is_self": true,
  "media": null,
  "is_video": false,
  "sensitive": false,
  "the_new_excerpt": ""
}