{
  "created_at": "2021-12-13T01:45:26.085Z",
  "title": "Sending SMS Messages Through the ISS (2020)",
  "url": "https://www.kj7nzl.net/blog/sending-sms-messages-through-iss/",
  "author": "squidhunter",
  "points": 169,
  "num_comments": 18,
  "_tags": [
    "story",
    "author_squidhunter",
    "story_29530400",
    "front_page"
  ],
  "objectID": "29530400",
  "original_created_at": "2021-12-12T15:34:06.000Z",
  "image": "https://www.kj7nzl.net/img/aprs/aprs-iss-sms-0001.webp",
  "localize": [
    {
      "locale": "ja",
      "title": "ISSを通じてSMSメッセージを送信（2020年）"
    },
    {
      "locale": "zh",
      "title": "通过国际空间站发送短信 (2020)"
    },
    {
      "locale": "zh-Hant",
      "title": "通過國際空間站發送短信 (2020)"
    }
  ],
  "source_updated_at": 1639734126750
}