{
  "created_at": "Thu Aug 11 12:57:29 +0000 2022",
  "id_str": "1557683280840892419",
  "full_text": "Few African regions have the nerve to say no to China. Independence-minded Somaliland is one. “We’re not going to allow anyone to dictate who we can have a relationship with.” https://t.co/9eSFFEHGOF",
  "display_text_range": [
    0,
    199
  ],
  "entities": {
    "hashtags": [],
    "symbols": [],
    "user_mentions": [],
    "urls": [
      {
        "url": "https://t.co/9eSFFEHGOF",
        "expanded_url": "https://on.wsj.com/3Qjf8qi",
        "display_url": "on.wsj.com/3Qjf8qi",
        "indices": [
          176,
          199
        ]
      }
    ]
  },
  "user": {
    "name": "The Wall Street Journal",
    "screen_name": "WSJ",
    "profile_image_url_https": "https://pbs.twimg.com/profile_images/971415515754266624/zCX0q9d5_normal.jpg"
  },
  "retweet_count": 34,
  "favorite_count": 133,
  "possibly_sensitive": false,
  "original_created_at": "Thu Aug 11 11:00:09 +0000 2022"
}