{
  "author": "msing539",
  "original_created_utc": 1637856520,
  "title": "How do you tell your significant other you're going to take a dump?",
  "created_utc": 1637861347,
  "selftext_html": "<!-- SC_OFF --><div class=\"md\"><p>In terms of phrasing. Like I&#39;m going to take a crap, shit, dump, poo, dookie squat? Surely there&#39;s some creative phrasing for this.</p>\n</div><!-- SC_ON -->",
  "score": 126,
  "permalink": "/r/NoStupidQuestions/comments/r1zwja/how_do_you_tell_your_significant_other_youre/",
  "subreddit": "NoStupidQuestions",
  "id": "r1zwja",
  "is_self": true,
  "media": null,
  "is_video": false,
  "the_new_excerpt": "In terms of phrasing. Like I'm going to take a crap, shit, dump, poo, dookie\nsquat? Surely there's some creative phrasing for this.",
  "localize": [
    {
      "locale": "ja",
      "the_new_excerpt": "フレーズ的には I'm going to take a crap, shit, dump, poo, dookie のように。\nsquat? きっと何かクリエイティブな言い回しがあるのでしょう。",
      "title": "大切な人にどうやってウンコをすることを伝えますか？"
    },
    {
      "locale": "zh",
      "the_new_excerpt": "在措辞方面。就像我要去拉屎，拉屎，拉屎，拉屎，拉尿一样\n蹲下？肯定有一些创造性的措辞来表达。",
      "title": "你如何告诉你的另一半你要去拉屎？"
    },
    {
      "locale": "zh-Hant",
      "the_new_excerpt": "在措辭方面。就像我要去拉屎，拉屎，拉屎，拉屎，拉尿一樣\n蹲下？肯定有一些創造性的措辭來表達。",
      "title": "你如何告訴你的另一半你要去拉屎？"
    }
  ]
}