{
  "id": "315669",
  "commentsCount": 7,
  "createdAt": "2021-10-12T18:26:15.140Z",
  "description": "Nuxt 3 is finally out in beta. Based on Vue 3, Vite and Nitro to create modern web applications that can be deployed anywhere, including Vercel, Netlify and CloudFlare Workers. Nuxt is an open source framework under MIT license.",
  "featuredAt": null,
  "media": [
    {
      "type": "image",
      "url": "https://ph-files.imgix.net/79d112ff-1f37-4f41-83ce-466b8acee180.png?auto=format",
      "videoUrl": null
    },
    {
      "type": "image",
      "url": "https://ph-files.imgix.net/03ce773b-dd14-43b6-b8ed-a897a832ead2.png?auto=format",
      "videoUrl": null
    }
  ],
  "name": "Nuxt 3 Beta",
  "productLinks": [
    {
      "type": "Website",
      "url": "https://www.producthunt.com/r/b8e85a3169320c?utm_campaign=producthunt-api&utm_medium=api-v2&utm_source=Application%3A+Buzzing+%28ID%3A+41381%29"
    }
  ],
  "user": {
    "name": "Sébastien Chopin",
    "url": "https://www.producthunt.com/@atinux?utm_campaign=producthunt-api&utm_medium=api-v2&utm_source=Application%3A+Buzzing+%28ID%3A+41381%29"
  },
  "reviewsCount": 5,
  "reviewsRating": 5,
  "slug": "nuxt-3-beta",
  "tagline": "The Hybrid Vue(3) Framework",
  "url": "https://www.producthunt.com/posts/nuxt-3-beta?utm_campaign=producthunt-api&utm_medium=api-v2&utm_source=Application%3A+Buzzing+%28ID%3A+41381%29",
  "votesCount": 115,
  "website": "https://www.producthunt.com/r/b8e85a3169320c?utm_campaign=producthunt-api&utm_medium=api-v2&utm_source=Application%3A+Buzzing+%28ID%3A+41381%29",
  "topics": {
    "edges": [
      {
        "node": {
          "name": "Productivity"
        }
      },
      {
        "node": {
          "name": "Developer Tools"
        }
      },
      {
        "node": {
          "name": "Tech"
        }
      }
    ]
  },
  "original_createdAt": "2021-10-12T14:27:16Z",
  "localize": [
    {
      "locale": "ja",
      "description": "Nuxt 3のベータ版がついに公開されました。Vue 3、Vite、Nitroをベースに、Vercel、Netlify、CloudFlare Workersなど、どこにでもデプロイ可能なモダンなWebアプリケーションを作成します。Nuxtは、MITライセンスのオープンソースフレームワークです。",
      "tagline": "ハイブリッドVue(3)フレームワーク"
    },
    {
      "locale": "zh",
      "description": "Nuxt 3终于推出了测试版。基于Vue 3、Vite和Nitro来创建现代网络应用，可以在任何地方部署，包括Vercel、Netlify和CloudFlare Workers。Nuxt是一个MIT许可的开源框架。",
      "tagline": "混合Vue(3)框架"
    },
    {
      "locale": "zh-Hant",
      "description": "Nuxt 3終於推出了測試版。基於Vue 3、Vite和Nitro來創建現代網絡應用，可以在任何地方部署，包括Vercel、Netlify和CloudFlare Workers。Nuxt是一個MIT許可的開源框架。",
      "tagline": "混合Vue(3)框架"
    }
  ],
  "source_updated_at": 1634290799013
}