{
  "author": "ddfish",
  "the_new_excerpt": "",
  "original_created_utc": 1608817136,
  "localize": [
    {
      "locale": "zh",
      "title": "1950年代的香烟和您的机上用餐。"
    },
    {
      "locale": "zh-Hant",
      "title": "1950年代的香菸和您的機上用餐。"
    }
  ],
  "title": "1950’s cigarettes with your inflight meal.",
  "created_utc": 1608900806,
  "selftext_html": null,
  "score": 76003,
  "preview": {
    "images": [
      {
        "source": {
          "url": "https://preview.redd.it/dzz8fx3s15761.jpg?auto=webp&s=f241f2b1ffb86921f27d65139f35006d089a7299",
          "width": 4032,
          "height": 3024
        },
        "resolutions": [
          {
            "url": "https://preview.redd.it/dzz8fx3s15761.jpg?width=108&crop=smart&auto=webp&s=80494ad107f413e5240ebeb12f58e75d592f0033",
            "width": 108,
            "height": 81
          },
          {
            "url": "https://preview.redd.it/dzz8fx3s15761.jpg?width=216&crop=smart&auto=webp&s=1d505170d7c8dfb1c74ebc0a96a491ebd8c7ea4a",
            "width": 216,
            "height": 162
          },
          {
            "url": "https://preview.redd.it/dzz8fx3s15761.jpg?width=320&crop=smart&auto=webp&s=63ec0e251ae9890fe241c3490e3f173e458ad921",
            "width": 320,
            "height": 240
          },
          {
            "url": "https://preview.redd.it/dzz8fx3s15761.jpg?width=640&crop=smart&auto=webp&s=febec8b5bb46991a8a2009a68d4d5a68037d94ae",
            "width": 640,
            "height": 480
          },
          {
            "url": "https://preview.redd.it/dzz8fx3s15761.jpg?width=960&crop=smart&auto=webp&s=6f1fb1951cbf64bfcca31489a5fe3f45c1465598",
            "width": 960,
            "height": 720
          },
          {
            "url": "https://preview.redd.it/dzz8fx3s15761.jpg?width=1080&crop=smart&auto=webp&s=60634d68e8e2c4749dac0b7cd5463933570ad483",
            "width": 1080,
            "height": 810
          }
        ],
        "variants": {},
        "id": "d67U_Bb26lZsBLIwwz8h0ChiPsOBkZyQq1ICGPT2VTA"
      }
    ],
    "enabled": true
  },
  "permalink": "/r/mildlyinteresting/comments/kjfkwv/1950s_cigarettes_with_your_inflight_meal/",
  "subreddit": "mildlyinteresting",
  "id": "kjfkwv",
  "is_self": false,
  "media": null,
  "is_video": false,
  "source_updated_at": 1609495322438
}