{
  "author": "zakaria20199",
  "the_new_excerpt": "",
  "original_created_utc": 1623419277,
  "localize": [
    {
      "locale": "ja",
      "title": "男性のピークはこの時でした。"
    },
    {
      "locale": "zh",
      "title": "这就是男人的巅峰时期"
    },
    {
      "locale": "zh-Hant",
      "title": "這就是男人的巔峯時期"
    }
  ],
  "title": "This is when Men peaked",
  "created_utc": 1623470000,
  "selftext_html": null,
  "score": 81638,
  "preview": {
    "images": [
      {
        "source": {
          "url": "https://external-preview.redd.it/E5_UpeqzciQ7kSri82PsGC8phupJEiFGlHGoeeqFq_c.png?format=pjpg&auto=webp&s=0b2b833c7695cead9286f792a0279d77c0e78991",
          "width": 720,
          "height": 1136
        },
        "resolutions": [
          {
            "url": "https://external-preview.redd.it/E5_UpeqzciQ7kSri82PsGC8phupJEiFGlHGoeeqFq_c.png?width=108&crop=smart&format=pjpg&auto=webp&s=04ed7de835c6fdf05155ac8cef0101d8c65a5e36",
            "width": 108,
            "height": 170
          },
          {
            "url": "https://external-preview.redd.it/E5_UpeqzciQ7kSri82PsGC8phupJEiFGlHGoeeqFq_c.png?width=216&crop=smart&format=pjpg&auto=webp&s=5fe3094d00b7c43ad249a7cd062601ed5a3be17c",
            "width": 216,
            "height": 340
          },
          {
            "url": "https://external-preview.redd.it/E5_UpeqzciQ7kSri82PsGC8phupJEiFGlHGoeeqFq_c.png?width=320&crop=smart&format=pjpg&auto=webp&s=0b661be001bad7efa6798faf0fb3e2f3b3d47161",
            "width": 320,
            "height": 504
          },
          {
            "url": "https://external-preview.redd.it/E5_UpeqzciQ7kSri82PsGC8phupJEiFGlHGoeeqFq_c.png?width=640&crop=smart&format=pjpg&auto=webp&s=464ac857269945fb5ef5c64f1e5584a08524b394",
            "width": 640,
            "height": 1009
          }
        ],
        "variants": {},
        "id": "YQhZxOhv1kNAr04YMnytwzAPZa2lP-xaQzbbcGaN3DE"
      }
    ],
    "enabled": false
  },
  "permalink": "/r/memes/comments/nxge52/this_is_when_men_peaked/",
  "subreddit": "memes",
  "id": "nxge52",
  "is_self": false,
  "media": {
    "reddit_video": {
      "bitrate_kbps": 4800,
      "fallback_url": "https://v.redd.it/9lx4pykc5n471/DASH_1080.mp4?source=fallback",
      "height": 1080,
      "width": 684,
      "scrubber_media_url": "https://v.redd.it/9lx4pykc5n471/DASH_96.mp4",
      "dash_url": "https://v.redd.it/9lx4pykc5n471/DASHPlaylist.mpd?a=1626061999%2CMzBmOGI0MDNiMDU4NzFiOTQ0ZjM3YzgyOTUxN2FjYTA4ZWU2NTU5OWY5ZmIwYjU3YTE5NGI5MjYxZWJiODg3NQ%3D%3D&v=1&f=sd",
      "duration": 25,
      "hls_url": "https://v.redd.it/9lx4pykc5n471/HLSPlaylist.m3u8?a=1626061999%2CN2Q0ZTM2YTFhNjg3N2RlZTFiNGU3ZmUzZDU0ZWM1ZmYwYjQxY2I0MTA0ZWZjMzBlMDQ1YTFhNjQyOGQ2MGYzZA%3D%3D&v=1&f=sd",
      "is_gif": true,
      "transcoding_status": "completed"
    }
  },
  "is_video": true,
  "source_updated_at": 1624009730088
}